MANIFEST.in
README.md
setup.py
biovec/__init__.py
biovec/utils.py
biovec.egg-info/PKG-INFO
biovec.egg-info/SOURCES.txt
biovec.egg-info/dependency_links.txt
biovec.egg-info/requires.txt
biovec.egg-info/top_level.txt
biovec/models/__init__.py
biovec/models/prot_vec.py