Metadata-Version: 1.2
Name: biovec
Version: 0.2.7
Summary: A new approach for representing biological sequences
Home-page: https://github.com/kyu999/biovec
Author: kyu999
Author-email: kyukokkyou999@gmail.com
Maintainer: kyu999
Maintainer-email: kyukokkyou999@gmail.com
License: MIT
Platform: UNKNOWN
